azureml/__init__.py
azureml/acft/__init__.py
azureml/acft/multimodal/__init__.py
azureml/acft/multimodal/components/NOTICE.txt
azureml/acft/multimodal/components/__init__.py
azureml/acft/multimodal/components/_version.py
azureml/acft/multimodal/components/base_runner.py
azureml/acft/multimodal/components/task_factory.py
azureml/acft/multimodal/components/artifacts/__init__.py
azureml/acft/multimodal/components/artifacts/model.py
azureml/acft/multimodal/components/artifacts/multimodal_clip_predict.py
azureml/acft/multimodal/components/artifacts/multimodal_mmeft_predict.py
azureml/acft/multimodal/components/artifacts/preprocessor.py
azureml/acft/multimodal/components/artifacts/tokenizer.py
azureml/acft/multimodal/components/collators/__init__.py
azureml/acft/multimodal/components/collators/collators.py
azureml/acft/multimodal/components/constants/__init__.py
azureml/acft/multimodal/components/constants/constants.py
azureml/acft/multimodal/components/data/__init__.py
azureml/acft/multimodal/components/data/dataset.py
azureml/acft/multimodal/components/data/mltable_helper.py
azureml/acft/multimodal/components/data/utils.py
azureml/acft/multimodal/components/image_transformations/__init__.py
azureml/acft/multimodal/components/image_transformations/transformations.py
azureml/acft/multimodal/components/mlflow/__init__.py
azureml/acft/multimodal/components/mlflow/conda.yaml
azureml/acft/multimodal/components/mlflow/mlflow_model_wrapper.py
azureml/acft/multimodal/components/mlflow/mlflow_save_utils.py
azureml/acft/multimodal/components/mlflow/utils.py
azureml/acft/multimodal/components/model/__init__.py
azureml/acft/multimodal/components/model/mmeft/__init__.py
azureml/acft/multimodal/components/model/mmeft/constants.py
azureml/acft/multimodal/components/model/mmeft/mm_early_fusion_config.py
azureml/acft/multimodal/components/model/mmeft/mm_early_fusion_model.py
azureml/acft/multimodal/components/model/mmeft/mm_early_fusion_classifier/__init__.py
azureml_acft_multimodal_components-47.0.0.dist-info/LICENSE.txt
azureml_acft_multimodal_components-47.0.0.dist-info/METADATA
azureml_acft_multimodal_components-47.0.0.dist-info/WHEEL
azureml_acft_multimodal_components-47.0.0.dist-info/top_level.txt
azureml_acft_multimodal_components-47.0.0.dist-info/RECORD
